basicmicro/__init__.py
basicmicro/commands.py
basicmicro/controller.py
basicmicro/exceptions.py
basicmicro/types.py
basicmicro/utils.py
basicmicro-2.0.8.dist-info/licenses/LICENSE
basicmicro-2.0.8.dist-info/METADATA
basicmicro-2.0.8.dist-info/WHEEL
basicmicro-2.0.8.dist-info/top_level.txt
basicmicro-2.0.8.dist-info/RECORD
