Metadata-Version: 2.4
Name: basicmicro
Version: 2.0.8
Summary: A modernized Python 3 library for controlling Basicmicro motor controllers
Home-page: https://github.com/acidtech/basicmicro_python
Author: Nathan Scherdin
Author-email: support@basicmicro.com
Keywords: robotics,motor control,basicmicro,roboclaw,serial
Classifier: Programming Language :: Python :: 3
Classifier: Programming Language :: Python :: 3.6
Classifier: Programming Language :: Python :: 3.7
Classifier: Programming Language :: Python :: 3.8
Classifier: Programming Language :: Python :: 3.9
Classifier: Programming Language :: Python :: 3.10
Classifier: Programming Language :: Python :: 3.11
Classifier: Programming Language :: Python :: 3.12
Classifier: Programming Language :: Python :: 3.13
Classifier: License :: OSI Approved :: MIT License
Classifier: Operating System :: OS Independent
Classifier: Development Status :: 5 - Production/Stable
Classifier: Intended Audience :: Developers
Classifier: Intended Audience :: Science/Research
Classifier: Topic :: Software Development :: Libraries :: Python Modules
Classifier: Topic :: Scientific/Engineering :: Interface Engine/Protocol Translator
Requires-Python: >=3.6
License-File: LICENSE
Requires-Dist: pyserial>=3.4
Dynamic: author
Dynamic: author-email
Dynamic: classifier
Dynamic: description
Dynamic: description-content-type
Dynamic: home-page
Dynamic: keywords
Dynamic: license-file
Dynamic: requires-dist
Dynamic: requires-python
Dynamic: summary
